neutronapi/__init__.py
neutronapi/application.py
neutronapi/background.py
neutronapi/base.py
neutronapi/cli.py
neutronapi/encoders.py
neutronapi/exceptions.py
neutronapi/multipart.py
neutronapi/authentication/__init__.py
neutronapi/authentication/base.py
neutronapi/commands/__init__.py
neutronapi/commands/migrate.py
neutronapi/commands/shell.py
neutronapi/commands/start.py
neutronapi/commands/startapp.py
neutronapi/commands/startproject.py
neutronapi/commands/test.py
neutronapi/db/__init__.py
neutronapi/db/connection.py
neutronapi/db/fields.py
neutronapi/db/migrations.py
neutronapi/db/models.py
neutronapi/db/queryset.py
neutronapi/db/providers/__init__.py
neutronapi/db/providers/base.py
neutronapi/db/providers/postgres.py
neutronapi/db/providers/sqlite.py
neutronapi/middleware/__init__.py
neutronapi/middleware/allowed_hosts.py
neutronapi/middleware/cors.py
neutronapi/middleware/routing.py
neutronapi/openapi/__init__.py
neutronapi/openapi/openapi.py
neutronapi/openapi/swagger.py
neutronapi_test_aaron-0.1.0.dist-info/licenses/LICENSE
neutronapi_test_aaron-0.1.0.dist-info/METADATA
neutronapi_test_aaron-0.1.0.dist-info/WHEEL
neutronapi_test_aaron-0.1.0.dist-info/entry_points.txt
neutronapi_test_aaron-0.1.0.dist-info/top_level.txt
neutronapi_test_aaron-0.1.0.dist-info/RECORD
