Metadata-Version: 2.4
Name: neutronapi-test-aaron
Version: 0.1.0
Summary: High-performance Python framework built directly on uvicorn with built-in database models, migrations, and background tasks. Django that was built async-first.
Author-email: Aaron Kazah <aaron@neutronapi.com>
License-Expression: MIT
Keywords: api,framework,async,django,fastapi,uvicorn,orm,migrations,background-tasks
Classifier: Development Status :: 4 - Beta
Classifier: Intended Audience :: Developers
Classifier: Operating System :: OS Independent
Classifier: Programming Language :: Python :: 3
Classifier: Programming Language :: Python :: 3.9
Classifier: Programming Language :: Python :: 3.10
Classifier: Programming Language :: Python :: 3.11
Classifier: Programming Language :: Python :: 3.12
Classifier: Topic :: Internet :: WWW/HTTP :: HTTP Servers
Classifier: Topic :: Software Development :: Libraries :: Python Modules
Classifier: Framework :: AsyncIO
Requires-Python: >=3.9
License-File: LICENSE
Requires-Dist: uvicorn[standard]>=0.23.0
Requires-Dist: aiosqlite>=0.19.0
Requires-Dist: PyJWT>=2.8.0
Provides-Extra: postgres
Requires-Dist: asyncpg>=0.29.0; extra == "postgres"
Provides-Extra: dev
Requires-Dist: httpx>=0.24.0; extra == "dev"
Requires-Dist: pytest>=7.0.0; extra == "dev"
Requires-Dist: pytest-asyncio>=0.21.0; extra == "dev"
Dynamic: license-file
